geometry98765/__init__.py
geometry98765/add.py
geometry98765/circle.py
geometry98765/rectangle.py
geometry98765-0.1.dist-info/METADATA
geometry98765-0.1.dist-info/WHEEL
geometry98765-0.1.dist-info/top_level.txt
geometry98765-0.1.dist-info/RECORD
