Metadata-Version: 2.1
Name: geometry98765
Version: 0.1
Summary: A simple Python library for calculating the area of geometric shapes.
Home-page: UNKNOWN
Author: abcd
License: UNKNOWN
Platform: UNKNOWN
